changelogmanager/__init__.py
changelogmanager/__main__.py
changelogmanager/change_types.py
changelogmanager/changelog.py
changelogmanager/changelog_reader.py
changelogmanager/cli.py
changelogmanager/config.py
changelogmanager/github.py
keepachangelog_manager-4.0.0.dist-info/licenses/LICENSE.md
tests/__init__.py
tests/changelog_test.py
tests/utils.py
keepachangelog_manager-4.0.0.dist-info/METADATA
keepachangelog_manager-4.0.0.dist-info/WHEEL
keepachangelog_manager-4.0.0.dist-info/entry_points.txt
keepachangelog_manager-4.0.0.dist-info/top_level.txt
keepachangelog_manager-4.0.0.dist-info/zip-safe
keepachangelog_manager-4.0.0.dist-info/RECORD
