Metadata-Version: 2.4
Name: keepachangelog-manager
Version: 4.0.0
Summary: Python package allowing you to manage your `CHANGELOG.md` files
Home-page: https://github.com/tomtom-international/keepachangelog-manager
License: Apache License 2.0
Project-URL: Bug Tracker, https://github.com/tomtom-international/keepachangelog-manager/issues
Project-URL: Source Code, https://github.com/tomtom-international/keepachangelog-manager
Classifier: License :: OSI Approved :: Apache Software License
Requires-Python: >=3.9
License-File: LICENSE.md
Requires-Dist: Click<9,>=8.2.1
Requires-Dist: pyyaml<7,>=6.0.2
Requires-Dist: semantic_version<3,>=2.10.0
Requires-Dist: keepachangelog<3,>=2.0.0
Requires-Dist: urllib3<3,>=2.4.0
Requires-Dist: llvm-diagnostics<4,>=3.0.1
Requires-Dist: inquirer<4,>=3.4.0
Dynamic: classifier
Dynamic: description
Dynamic: description-content-type
Dynamic: home-page
Dynamic: license
Dynamic: license-file
Dynamic: project-url
Dynamic: requires-dist
Dynamic: requires-python
Dynamic: summary
